scoutml/__init__.py
scoutml/cli.py
scoutml/client.py
scoutml/config.py
scoutml/exceptions.py
scoutml/formatters.py
scoutml-0.1.5.dist-info/licenses/LICENSE
tests/__init__.py
tests/test_client.py
tests/test_config.py
tests/test_library.py
scoutml-0.1.5.dist-info/METADATA
scoutml-0.1.5.dist-info/WHEEL
scoutml-0.1.5.dist-info/entry_points.txt
scoutml-0.1.5.dist-info/top_level.txt
scoutml-0.1.5.dist-info/RECORD
